S2search/SearchScript.py
S2search/SearchWebScript.py
S2search/__init__.py
S2search-1.0.4.3.dist-info/LICENSE.md
S2search-1.0.4.3.dist-info/METADATA
S2search-1.0.4.3.dist-info/WHEEL
S2search-1.0.4.3.dist-info/top_level.txt
S2search-1.0.4.3.dist-info/RECORD
