Metadata-Version: 2.1
Name: S2search
Version: 1.0.4.3
Summary: Semantic Scholar paper api consuming
Author: BecomeAllan (Allan)
Author-email: <allan.filesia@gmail.com>
License: UNKNOWN
Keywords: python,Semantic Scholar,API,Papers,semantic-scholar,papers
Platform: UNKNOWN
Classifier: Development Status :: 3 - Alpha
Classifier: Intended Audience :: Developers
Classifier: Programming Language :: Python :: 3
Classifier: License :: OSI Approved :: MIT License
Classifier: Intended Audience :: Science/Research
Classifier: Operating System :: Unix
Classifier: Operating System :: MacOS :: MacOS X
Classifier: Operating System :: Microsoft :: Windows
Classifier: Topic :: Software Development :: Libraries :: Python Modules
License-File: LICENSE.md
Requires-Dist: requests
Requires-Dist: pandas
